treequest/__init__.py
treequest/imports.py
treequest/py.typed
treequest/ranker.py
treequest/trial.py
treequest/types.py
treequest/visualization.py
treequest/algos/base.py
treequest/algos/best_first_search.py
treequest/algos/multi_armed_bandit_ucb.py
treequest/algos/standard_mcts.py
treequest/algos/tree.py
treequest/algos/tree_of_thought_bfs.py
treequest/algos/ab_mcts_a/algo.py
treequest/algos/ab_mcts_a/prob_state.py
treequest/algos/ab_mcts_m/_ab_mcts_m_imports.py
treequest/algos/ab_mcts_m/algo.py
treequest/algos/ab_mcts_m/numpyro_utils.py
treequest/algos/ab_mcts_m/pymc_interface.py
treequest-0.2.0.dist-info/METADATA
treequest-0.2.0.dist-info/WHEEL
treequest-0.2.0.dist-info/licenses/LICENSE
treequest-0.2.0.dist-info/RECORD
