Metadata-Version: 2.4
Name: treequest
Version: 0.2.0
Summary: A Tree Search Library with Flexible API for LLM Inference-Time Scaling
Author-email: Kou Misaki <kou.misaki@sakana.ai>, Takuya Akiba <takiba@sakana.ai>
License-File: LICENSE
Requires-Python: >=3.11
Requires-Dist: joblib>=1.5.2
Requires-Dist: scipy>=1.0.0
Requires-Dist: ulid-py>=1.1.0
Provides-Extra: abmcts-m
Requires-Dist: jax>=0.5.2; extra == 'abmcts-m'
Requires-Dist: numpy>=1.26.4; extra == 'abmcts-m'
Requires-Dist: numpyro>=0.17.0; extra == 'abmcts-m'
Requires-Dist: packaging>=23; extra == 'abmcts-m'
Requires-Dist: pandas>=2.2.3; extra == 'abmcts-m'
Requires-Dist: pymc>=5.21.0; extra == 'abmcts-m'
Requires-Dist: xarray>=2025.1.2; extra == 'abmcts-m'
